automated_actions_cli/__init__.py
automated_actions_cli/__main__.py
automated_actions_cli/cli.py
automated_actions_cli/config.py
automated_actions_cli/formatter.py
automated_actions_cli/py.typed
automated_actions_cli/utils.py
automated_actions_cli-0.1.7.dist-info/METADATA
automated_actions_cli-0.1.7.dist-info/WHEEL
automated_actions_cli-0.1.7.dist-info/entry_points.txt
automated_actions_cli-0.1.7.dist-info/RECORD
