Metadata-Version: 2.4
Name: automated-actions-cli
Version: 0.1.7
Summary: Automated Actions Client
Project-URL: homepage, https://github.com/app-sre/automated-actions
Project-URL: repository, https://github.com/app-sre/automated-actions
Project-URL: documentation, https://github.com/app-sre/automated-actions
Author-email: AppSRE <sd-app-sre@redhat.com>
License: Apache 2.0
Requires-Python: ~=3.12.0
Requires-Dist: appdirs==1.4.4
Requires-Dist: automated-actions-client
Requires-Dist: diskcache==5.6.3
Requires-Dist: httpx-gssapi==0.5
Requires-Dist: packaging==25.0
Requires-Dist: pydantic-settings==2.11.0
Requires-Dist: pyyaml==6.0.3
Requires-Dist: rich==14.2.0
Requires-Dist: typer==0.20.0
